redux/__init__.py
redux/_version.py
redux/autorun.py
redux/basic_types.py
redux/combine_reducers.py
redux/main.py
redux/py.typed
redux/serialization_mixin.py
redux/side_effect_runner.py
redux/utils.py
redux_pytest/__init__.py
redux_pytest/plugin.py
redux_pytest/fixtures/__init__.py
redux_pytest/fixtures/event_loop.py
redux_pytest/fixtures/monitor.py
redux_pytest/fixtures/snapshot.py
redux_pytest/fixtures/store.py
redux_pytest/fixtures/wait_for.py
python_redux-0.25.0.dist-info/METADATA
python_redux-0.25.0.dist-info/WHEEL
python_redux-0.25.0.dist-info/entry_points.txt
python_redux-0.25.0.dist-info/licenses/LICENSE
python_redux-0.25.0.dist-info/RECORD
