Metadata-Version: 2.4
Name: python-redux
Version: 0.25.0
Summary: Redux implementation for Python (Binary Extension)
Home-page: https://github.com/sassanh/python-redux/
Author: Sassan Haradji
Author-email: me@sassanh.com
License-File: LICENSE
Dynamic: author
Dynamic: author-email
Dynamic: home-page
Dynamic: license-file
Dynamic: summary
